brainmodeling/__init__.py
brainmodeling/tests/test_version.py
brainmodeling-2025.5.4.dist-info/LICENSE
brainmodeling-2025.5.4.dist-info/METADATA
brainmodeling-2025.5.4.dist-info/WHEEL
brainmodeling-2025.5.4.dist-info/top_level.txt
brainmodeling-2025.5.4.dist-info/RECORD
